{
  "main": {
    "id": "8e703a46b4bd4f23",
    "type": "split",
    "children": [
      {
        "id": "1bfbe83e9dd7c959",
        "type": "tabs",
        "children": [
          {
            "id": "f747227d4b1a4129",
            "type": "leaf",
            "state": {
              "type": "markdown",
              "state": {
                "file": "Конспекты лекций/Лекция 3 - Ethernet.md",
                "mode": "source",
                "source": false
              }
            }
          }
        ]
      }
    ],
    "direction": "vertical"
  },
  "left": {
    "id": "2f041121e05378cc",
    "type": "split",
    "children": [
      {
        "id": "062a929c2de86d6f",
        "type": "tabs",
        "children": [
          {
            "id": "9cea649a0ec0df22",
            "type": "leaf",
            "state": {
              "type": "file-explorer",
              "state": {
                "sortOrder": "alphabetical"
              }
            }
          },
          {
            "id": "71894d19938cd216",
            "type": "leaf",
            "state": {
              "type": "search",
              "state": {
                "query": "",
                "matchingCase": false,
                "explainSearch": false,
                "collapseAll": false,
                "extraContext": false,
                "sortOrder": "alphabetical"
              }
            }
          },
          {
            "id": "ea24c4963dea2141",
            "type": "leaf",
            "state": {
              "type": "bookmarks",
              "state": {}
            }
          }
        ]
      }
    ],
    "direction": "horizontal",
    "width": 300
  },
  "right": {
    "id": "bcf602ea4a05b79a",
    "type": "split",
    "children": [
      {
        "id": "9f0ccd58cdd720f4",
        "type": "tabs",
        "children": [
          {
            "id": "e2ce2cbebe02d028",
            "type": "leaf",
            "state": {
              "type": "backlink",
              "state": {
                "file": "Конспекты лекций/Лекция 3 - Ethernet.md",
                "collapseAll": false,
                "extraContext": false,
                "sortOrder": "alphabetical",
                "showSearch": false,
                "searchQuery": "",
                "backlinkCollapsed": false,
                "unlinkedCollapsed": true
              }
            }
          },
          {
            "id": "b127cd29176e23d9",
            "type": "leaf",
            "state": {
              "type": "outgoing-link",
              "state": {
                "file": "Конспекты лекций/Лекция 3 - Ethernet.md",
                "linksCollapsed": false,
                "unlinkedCollapsed": true
              }
            }
          },
          {
            "id": "a9ce4330e4ac2500",
            "type": "leaf",
            "state": {
              "type": "tag",
              "state": {
                "sortOrder": "frequency",
                "useHierarchy": true
              }
            }
          },
          {
            "id": "e7e4883ddf4883ae",
            "type": "leaf",
            "state": {
              "type": "outline",
              "state": {
                "file": "Конспекты лекций/Лекция 3 - Ethernet.md"
              }
            }
          }
        ]
      }
    ],
    "direction": "horizontal",
    "width": 300,
    "collapsed": true
  },
  "left-ribbon": {
    "hiddenItems": {
      "switcher:Open quick switcher": false,
      "graph:Open graph view": false,
      "canvas:Create new canvas": false,
      "daily-notes:Open today's daily note": false,
      "templates:Insert template": false,
      "command-palette:Open command palette": false
    }
  },
  "active": "f747227d4b1a4129",
  "lastOpenFiles": []
}